{ "height":30,
 "infinite":false,
 "layers":[
        {
         "data":[9, 9, 9, 9, 9, 9, 9, 9, 9, 9, 9, 9, 9, 9, 9, 9, 9, 9, 9, 9, 9, 9, 9, 9, 9, 9, 9, 9, 9, 9, 9, 9, 9, 9, 21, 13, 13, 13, 13, 22, 9, 21, 13, 13, 13, 13, 13, 13, 13, 13, 13, 13, 13, 13, 13, 13, 13, 13, 13, 13, 13, 13, 13, 13, 13, 13, 13, 13, 13, 13, 13, 13, 13, 13, 15, 2, 2, 2, 2, 19, 9, 20, 2, 2, 2, 33, 2, 2, 2, 2, 2, 2, 2, 2, 2, 2, 2, 2, 2, 2, 2, 2, 2, 2, 2, 2, 33, 2, 2, 2, 2, 2, 2, 2, 2, 2, 2, 2, 2, 19, 9, 20, 2, 2, 2, 2, 2, 2, 2, 2, 2, 2, 2, 2, 2, 2, 2, 2, 2, 2, 2, 2, 2, 2, 2, 2, 2, 2, 2, 2, 2, 2, 2, 2, 2, 2, 2, 33, 2, 19, 9, 20, 2, 2, 17, 16, 16, 16, 16, 16, 16, 16, 16, 16, 16, 16, 16, 16, 16, 16, 16, 18, 2, 2, 17, 16, 18, 2, 2, 17, 16, 16, 16, 16, 18, 2, 2, 2, 2, 19, 9, 20, 2, 2, 14, 13, 13, 13, 13, 13, 13, 13, 13, 13, 13, 13, 13, 13, 13, 13, 13, 15, 2, 2, 14, 13, 15, 2, 2, 19, 9, 9, 9, 9, 25, 16, 16, 16, 16, 23, 9, 20, 2, 2, 2, 2, 2, 2, 2, 2, 2, 2, 2, 2, 2, 2, 2, 2, 2, 2, 2, 33, 2, 2, 2, 2, 2, 2, 2, 19, 9, 66, 67, 68, 69, 70, 71, 72, 73, 9, 9, 20, 2, 2, 2, 2, 33, 2, 2, 2, 2, 2, 2, 2, 2, 2, 2, 2, 2, 2, 2, 2, 2, 2, 2, 2, 2, 2, 2, 19, 9, 74, 75, 76, 77, 78, 79, 80, 81, 9, 9, 20, 2, 2, 17, 18, 2, 2, 10, 8, 8, 8, 8, 8, 8, 31, 18, 2, 2, 10, 8, 8, 8, 8, 32, 18, 2, 2, 17, 23, 9, 82, 83, 84, 85, 86, 87, 88, 89, 9, 9, 20, 2, 2, 19, 20, 2, 2, 2, 2, 2, 2, 2, 2, 2, 19, 20, 2, 2, 2, 2, 2, 2, 2, 19, 20, 2, 2, 19, 9, 9, 9, 9, 9, 21, 13, 13, 13, 13, 22, 9, 20, 2, 2, 19, 20, 2, 2, 2, 2, 2, 2, 2, 2, 2, 19, 20, 2, 2, 2, 2, 2, 2, 2, 19, 20, 2, 2, 19, 9, 9, 21, 13, 13, 15, 2, 2, 2, 2, 19, 9, 20, 2, 2, 14, 28, 27, 27, 27, 27, 27, 27, 12, 2, 2, 14, 24, 8, 8, 8, 8, 12, 2, 2, 14, 15, 2, 2, 14, 13, 13, 15, 2, 2, 2, 2, 2, 2, 2, 19, 9, 20, 33, 2, 2, 2, 2, 2, 2, 2, 2, 2, 2, 2, 2, 2, 2, 2, 2, 2, 2, 2, 2, 2, 2, 2, 2, 2, 2, 2, 2, 2, 2, 2, 33, 2, 2, 2, 2, 19, 9, 20, 2, 2, 2, 2, 2, 2, 2, 2, 2, 2, 2, 2, 2, 2, 2, 33, 2, 2, 2, 2, 2, 2, 2, 2, 2, 2, 2, 2, 2, 2, 2, 2, 26, 2, 2, 2, 2, 19, 9, 20, 2, 2, 17, 18, 2, 2, 17, 16, 16, 16, 18, 2, 2, 17, 16, 16, 16, 16, 16, 18, 2, 2, 17, 16, 16, 16, 16, 18, 2, 2, 17, 16, 29, 16, 16, 16, 16, 23, 9, 20, 2, 2, 19, 20, 2, 2, 19, 9, 9, 9, 20, 2, 2, 19, 9, 9, 9, 9, 9, 20, 2, 2, 14, 13, 13, 13, 13, 15, 2, 2, 14, 13, 13, 13, 13, 13, 22, 9, 9, 20, 2, 2, 19, 20, 2, 2, 19, 9, 9, 9, 20, 2, 2, 19, 9, 9, 9, 9, 9, 20, 2, 2, 2, 2, 2, 2, 2, 2, 2, 2, 2, 2, 2, 2, 2, 2, 19, 9, 9, 20, 2, 2, 19, 20, 2, 2, 19, 21, 13, 13, 15, 2, 2, 14, 13, 13, 13, 22, 9, 20, 2, 2, 2, 2, 2, 2, 2, 2, 2, 2, 2, 2, 2, 2, 33, 2, 19, 9, 9, 20, 2, 2, 19, 20, 2, 2, 19, 20, 2, 33, 2, 2, 2, 2, 2, 2, 33, 19, 9, 20, 2, 2, 17, 16, 16, 16, 16, 16, 16, 16, 16, 16, 16, 18, 2, 2, 19, 9, 9, 20, 2, 2, 19, 20, 2, 2, 19, 20, 2, 2, 2, 2, 2, 2, 2, 2, 2, 19, 9, 20, 2, 2, 19, 9, 9, 9, 9, 9, 9, 9, 9, 9, 9, 20, 2, 2, 19, 9, 9, 20, 2, 2, 19, 20, 2, 2, 19, 20, 2, 2, 30, 2, 2, 17, 18, 2, 2, 19, 9, 20, 2, 2, 19, 9, 9, 9, 9, 9, 9, 9, 21, 13, 13, 15, 2, 2, 14, 22, 9, 20, 2, 2, 14, 15, 2, 2, 19, 20, 2, 2, 11, 2, 2, 19, 20, 2, 2, 14, 13, 15, 2, 2, 14, 13, 13, 13, 13, 13, 13, 13, 15, 7, 7, 43, 44, 45, 7, 19, 9, 20, 2, 2, 2, 2, 2, 2, 19, 20, 2, 2, 11, 2, 2, 19, 20, 2, 2, 2, 2, 2, 2, 2, 2, 2, 2, 2, 2, 2, 2, 2, 2, 52, 53, 46, 47, 48, 7, 19, 9, 20, 33, 2, 2, 2, 2, 2, 19, 20, 2, 2, 11, 2, 2, 19, 20, 2, 2, 2, 2, 2, 2, 2, 2, 2, 2, 2, 2, 2, 2, 2, 2, 54, 55, 49, 50, 51, 7, 14, 9, 20, 2, 2, 17, 16, 16, 16, 23, 20, 2, 2, 11, 2, 2, 19, 25, 16, 16, 16, 16, 16, 16, 16, 16, 16, 16, 16, 16, 16, 16, 16, 18, 7, 7, 7, 7, 7, 7, 64, 9, 20, 2, 2, 14, 13, 13, 13, 13, 15, 2, 2, 11, 2, 2, 14, 13, 13, 13, 13, 13, 13, 13, 13, 13, 13, 13, 13, 13, 13, 13, 13, 15, 7, 7, 7, 7, 7, 7, 65, 9, 20, 2, 2, 2, 2, 2, 2, 2, 2, 2, 2, 11, 2, 2, 2, 2, 33, 2, 2, 2, 2, 2, 2, 2, 2, 2, 2, 2, 33, 2, 2, 2, 37, 38, 7, 7, 7, 7, 17, 9, 20, 2, 2, 2, 2, 33, 2, 2, 2, 2, 2, 11, 2, 2, 2, 2, 2, 2, 2, 2, 2, 2, 2, 2, 2, 2, 2, 2, 2, 2, 2, 2, 39, 40, 7, 62, 60, 61, 19, 9, 25, 16, 16, 16, 16, 16, 16, 16, 16, 16, 16, 29, 16, 16, 16, 16, 16, 16, 16, 16, 16, 16, 16, 16, 16, 16, 16, 16, 16, 16, 16, 18, 41, 42, 7, 63, 60, 61, 19, 9, 9, 9, 9, 9, 9, 9, 9, 9, 9, 9, 9, 9, 9, 9, 9, 9, 9, 9, 9, 9, 9, 9, 9, 9, 9, 9, 9, 9, 9, 9, 9, 25, 16, 16, 16, 16, 16, 16, 23],
         "height":30,
         "name":"Tile Layer 1",
         "opacity":1,
         "type":"tilelayer",
         "visible":true,
         "width":40,
         "x":0,
         "y":0
        }],
 "nextobjectid":1,
 "orientation":"orthogonal",
 "renderorder":"right-down",
 "tiledversion":"1.1.5",
 "tileheight":16,
 "tilesets":[
        {
         "firstgid":1,
         "source":"..\/..\/Downloads\/git\/c4t-titlemap-starter\/assets\/maps\/flood3.tsx"
        }, 
        {
         "firstgid":2,
         "source":"..\/..\/Downloads\/git\/c4t-titlemap-starter\/assets\/maps\/flood1.tsx"
        }, 
        {
         "firstgid":3,
         "source":"..\/..\/Downloads\/git\/c4t-titlemap-starter\/assets\/maps\/dirt.tsx"
        }, 
        {
         "firstgid":7,
         "source":"..\/..\/Downloads\/git\/c4t-titlemap-starter\/assets\/maps\/flood2.tsx"
        }, 
        {
         "firstgid":8,
         "source":"..\/..\/Downloads\/git\/c4t-titlemap-starter\/assets\/maps\/wal11.tsx"
        }, 
        {
         "firstgid":9,
         "source":"..\/..\/Downloads\/git\/c4t-titlemap-starter\/assets\/maps\/wall.tsx"
        }, 
        {
         "firstgid":10,
         "source":"..\/..\/Downloads\/git\/c4t-titlemap-starter\/assets\/maps\/wall11.tsx"
        }, 
        {
         "firstgid":11,
         "source":"..\/..\/Downloads\/git\/c4t-titlemap-starter\/assets\/maps\/wall10.tsx"
        }, 
        {
         "firstgid":12,
         "source":"..\/..\/Downloads\/git\/c4t-titlemap-starter\/assets\/maps\/wall12.tsx"
        }, 
        {
         "firstgid":13,
         "source":"..\/..\/Downloads\/git\/c4t-titlemap-starter\/assets\/maps\/wall2.tsx"
        }, 
        {
         "firstgid":14,
         "source":"..\/..\/Downloads\/git\/c4t-titlemap-starter\/assets\/maps\/wall3.tsx"
        }, 
        {
         "firstgid":15,
         "source":"..\/..\/Downloads\/git\/c4t-titlemap-starter\/assets\/maps\/wall4.tsx"
        }, 
        {
         "firstgid":16,
         "source":"..\/..\/Downloads\/git\/c4t-titlemap-starter\/assets\/maps\/wall5.tsx"
        }, 
        {
         "firstgid":17,
         "source":"..\/..\/Downloads\/git\/c4t-titlemap-starter\/assets\/maps\/wall6.tsx"
        }, 
        {
         "firstgid":18,
         "source":"..\/..\/Downloads\/git\/c4t-titlemap-starter\/assets\/maps\/wall7.tsx"
        }, 
        {
         "firstgid":19,
         "source":"..\/..\/Downloads\/git\/c4t-titlemap-starter\/assets\/maps\/wall8.tsx"
        }, 
        {
         "firstgid":20,
         "source":"..\/..\/Downloads\/git\/c4t-titlemap-starter\/assets\/maps\/wall9.tsx"
        }, 
        {
         "firstgid":21,
         "source":"..\/..\/Downloads\/git\/c4t-titlemap-starter\/assets\/maps\/wall14.tsx"
        }, 
        {
         "firstgid":22,
         "source":"..\/..\/Downloads\/git\/c4t-titlemap-starter\/assets\/maps\/wall15.tsx"
        }, 
        {
         "firstgid":23,
         "source":"..\/..\/Downloads\/git\/c4t-titlemap-starter\/assets\/maps\/wall16.tsx"
        }, 
        {
         "firstgid":24,
         "source":"..\/..\/Downloads\/git\/c4t-titlemap-starter\/assets\/maps\/wall 13.tsx"
        }, 
        {
         "firstgid":25,
         "source":"..\/..\/Downloads\/git\/c4t-titlemap-starter\/assets\/maps\/wall 1-1.tsx"
        }, 
        {
         "firstgid":26,
         "source":"..\/..\/Downloads\/git\/c4t-titlemap-starter\/assets\/maps\/wall17.tsx"
        }, 
        {
         "firstgid":27,
         "source":"..\/..\/Downloads\/git\/c4t-titlemap-starter\/assets\/maps\/wall1-3.tsx"
        }, 
        {
         "firstgid":28,
         "source":"..\/..\/Downloads\/git\/c4t-titlemap-starter\/assets\/maps\/wall1-4.tsx"
        }, 
        {
         "firstgid":29,
         "source":"..\/..\/Downloads\/git\/c4t-titlemap-starter\/assets\/maps\/wall1-5.tsx"
        }, 
        {
         "firstgid":30,
         "source":"..\/..\/Downloads\/git\/c4t-titlemap-starter\/assets\/maps\/wall1-6.tsx"
        }, 
        {
         "firstgid":31,
         "source":"..\/..\/Downloads\/git\/c4t-titlemap-starter\/assets\/maps\/wall1-7.tsx"
        }, 
        {
         "firstgid":32,
         "source":"..\/..\/Downloads\/git\/c4t-titlemap-starter\/assets\/maps\/wall1-2.tsx"
        }, 
        {
         "firstgid":33,
         "source":"..\/..\/Downloads\/git\/c4t-titlemap-starter\/assets\/maps\/new rocks.tsx"
        }, 
        {
         "firstgid":34,
         "source":"..\/..\/Downloads\/git\/c4t-titlemap-starter\/assets\/maps\/rocks.tsx"
        }, 
        {
         "firstgid":35,
         "source":"..\/..\/Downloads\/git\/c4t-titlemap-starter\/assets\/maps\/light 2.tsx"
        }, 
        {
         "firstgid":37,
         "source":"..\/..\/Downloads\/git\/c4t-titlemap-starter\/assets\/maps\/broken door.tsx"
        }, 
        {
         "firstgid":43,
         "source":"..\/..\/Downloads\/git\/c4t-titlemap-starter\/assets\/maps\/broken door 1-1.tsx"
        }, 
        {
         "firstgid":52,
         "source":"..\/..\/Downloads\/git\/c4t-titlemap-starter\/assets\/maps\/broen door 1-2.tsx"
        }, 
        {
         "firstgid":56,
         "source":"..\/..\/Downloads\/git\/c4t-titlemap-starter\/assets\/maps\/dirt foor 2-0.tsx"
        }, 
        {
         "firstgid":60,
         "source":"..\/..\/Downloads\/git\/c4t-titlemap-starter\/assets\/maps\/bed 1-0.tsx"
        }, 
        {
         "firstgid":62,
         "source":"..\/..\/Downloads\/git\/c4t-titlemap-starter\/assets\/maps\/bed 1-1.tsx"
        }, 
        {
         "firstgid":64,
         "source":"..\/..\/Downloads\/git\/c4t-titlemap-starter\/assets\/maps\/flood-dirt 1-0.tsx"
        }, 
        {
         "firstgid":66,
         "source":"..\/..\/Downloads\/git\/c4t-titlemap-starter\/assets\/maps\/not yet.tsx"
        }],
 "tilewidth":16,
 "type":"map",
 "version":1,
 "width":40
}